nlp2024/__cli__.py
nlp2024/__init__.py
nlp2024/_version.py
nlp2024/conf/about/nlp2024.yaml
nlp2024/py.typed
intronlp_2024-0.6.0.dist-info/LICENSE
intronlp_2024-0.6.0.dist-info/METADATA
intronlp_2024-0.6.0.dist-info/WHEEL
intronlp_2024-0.6.0.dist-info/entry_points.txt
intronlp_2024-0.6.0.dist-info/RECORD
