Metadata-Version: 2.1
Name: intronlp-2024
Version: 0.6.0
Summary: Introduction to the fundamental concepts of Natural Language Processing (NLP) and advanced language model technologies.
Home-page: https://nlp2024.jeju.ai
License: CC-BY-4.0
Author: Young Joon Lee
Author-email: entelecheia@hotmail.com
Requires-Python: >=3.9,<3.13
Classifier: License :: Other/Proprietary License
Classifier: Programming Language :: Python :: 3
Classifier: Programming Language :: Python :: 3.9
Classifier: Programming Language :: Python :: 3.10
Classifier: Programming Language :: Python :: 3.11
Classifier: Programming Language :: Python :: 3.12
Requires-Dist: click (>=8.1.3,<9.0.0)
Requires-Dist: ekonlpy (>=2.0.5,<3.0.0)
Requires-Dist: gensim (>=4.3.0,<=4.3.3)
Requires-Dist: huggingface-hub (>=0.20.2,<=0.26.2)
Requires-Dist: matplotlib (>=3.9.0,<=3.9.2)
Requires-Dist: nltk (>=3.9.0,<=3.9.2)
Requires-Dist: numpy (>=1.26.4,<=2.0.0)
Requires-Dist: openai (>=1.44.0,<=1.54.3)
Requires-Dist: pyyaml (>=6.0.2,<7.0.0)
Requires-Dist: scikit-learn (>=1.3.2,<=1.5.2)
Project-URL: Repository, https://github.com/entelecheia/intronlp-2024
